amypad/__init__.py
amypad/imio/__init__.py
amypad/imio/nii.py
amypad/utils/__init__.py
amypad_core-0.0.3.dist-info/LICENCE.md
amypad_core-0.0.3.dist-info/METADATA
amypad_core-0.0.3.dist-info/WHEEL
amypad_core-0.0.3.dist-info/top_level.txt
amypad_core-0.0.3.dist-info/RECORD
